<launch>

  <arg name="launch_driver" default="true" />

  <group>
    <push-ros-namespace namespace="lidar"/>

    <group>
      <push-ros-namespace namespace="top"/>
      <include file="$(find-pkg-share sensing_launch)/launch/velodyne_VLS128.launch.xml">
        <arg name="sensor_frame" value="velodyne_top" />
        <arg name="device_ip" value="192.168.1.201"/>
        <arg name="port" value="2368"/>
        <arg name="launch_driver" value="$(var launch_driver)" />
      </include>
    </group>

    <group>
      <push-ros-namespace namespace="left"/>
      <include file="$(find-pkg-share sensing_launch)/launch/velodyne_VLP16.launch.xml">
        <arg name="sensor_frame" value="velodyne_left" />
        <arg name="device_ip" value="192.168.1.202"/>
        <arg name="port" value="2369"/>
        <arg name="launch_driver" value="$(var launch_driver)" />
      </include>
    </group>

    <group>
      <push-ros-namespace namespace="right"/>
      <include file="$(find-pkg-share sensing_launch)/launch/velodyne_VLP16.launch.xml">
        <arg name="sensor_frame" value="velodyne_right" />
        <arg name="device_ip" value="192.168.1.203"/>
        <arg name="port" value="2370"/>
        <arg name="launch_driver" value="$(var launch_driver)" />
      </include>
    </group>

    <include file="$(find-pkg-share sensing_launch)/launch/aip_xx2/pointcloud_preprocessor.launch.py">
      <arg name="base_frame" value="base_link" />
    </include>

  </group>
</launch>
